converter.py
heic_to_jpeg_converter-1.0.4.dist-info/LICENSE
heic_to_jpeg_converter-1.0.4.dist-info/METADATA
heic_to_jpeg_converter-1.0.4.dist-info/WHEEL
heic_to_jpeg_converter-1.0.4.dist-info/entry_points.txt
heic_to_jpeg_converter-1.0.4.dist-info/top_level.txt
heic_to_jpeg_converter-1.0.4.dist-info/RECORD
