Metadata-Version: 2.1
Name: heic-to-jpeg-converter
Version: 1.0.4
Summary: HEIC to JPEG Converter
Home-page: https://github.com/ushruffi/heic-to-jpeg-converter
Author: Talal Ashraf
Author-email: ushruffi@gmail.com
License: MIT License
Platform: UNKNOWN
Classifier: Programming Language :: Python :: 3.9
Classifier: Operating System :: OS Independent
Requires-Python: >=3.9
Requires-Dist: cffi (==1.14.5)
Requires-Dist: click (==7.1.2)
Requires-Dist: Pillow (==8.1.2)
Requires-Dist: pycparser (==2.20)
Requires-Dist: pyheif (==0.5.1)
